khapitools/__init__.py
khapitools/core.py
khapitools/views.py
khapitools/migrations/__init__.py
khapitools-0.1.0.dist-info/METADATA
khapitools-0.1.0.dist-info/WHEEL
khapitools-0.1.0.dist-info/licenses/LICENSE
khapitools-0.1.0.dist-info/RECORD
