Metadata-Version: 2.1
Name: khapitools
Version: 0.1.0
Summary: Image Search API for Khapi package
Project-URL: Homepage, https://github.com/khfix/khapitools
Project-URL: Issues, https://github.com/khfix/khapitools/issues
Author-email: khfix <hamza.alkhatib.se@gmail.com>
License-File: LICENSE
Classifier: License :: OSI Approved :: MIT License
Classifier: Operating System :: OS Independent
Classifier: Programming Language :: Python :: 3
Requires-Python: >=3.6
